for_django_projects/__init__.py
for_django_projects/alertas/__init__.py
for_django_projects/form_utils/__init__.py
for_django_projects/form_utils/admin.py
for_django_projects/form_utils/fields.py
for_django_projects/form_utils/forms.py
for_django_projects/form_utils/models.py
for_django_projects/form_utils/settings.py
for_django_projects/form_utils/utils.py
for_django_projects/form_utils/widgets.py
for_django_projects/form_utils/templates/form_utils/better_form.html
for_django_projects/form_utils/templates/form_utils/fields_as_lis.html
for_django_projects/form_utils/templates/form_utils/form.html
for_django_projects/form_utils/templatetags/__init__.py
for_django_projects/form_utils/templatetags/form_utils.py
for_django_projects/pwa/__init__.py
for_django_projects/pwa/app_settings.py
for_django_projects/pwa/apps.py
for_django_projects/pwa/urls.py
for_django_projects/pwa/views.py
for_django_projects/pwa/static/css/django-pwa-app.css
for_django_projects/pwa/static/fonts/bootstrap/glyphicons-halflings-regular.eot
for_django_projects/pwa/static/fonts/bootstrap/glyphicons-halflings-regular.svg
for_django_projects/pwa/static/fonts/bootstrap/glyphicons-halflings-regular.ttf
for_django_projects/pwa/static/fonts/bootstrap/glyphicons-halflings-regular.woff
for_django_projects/pwa/static/fonts/bootstrap/glyphicons-halflings-regular.woff2
for_django_projects/pwa/static/images/icons/Thumbs.db
for_django_projects/pwa/static/images/icons/icon-128x128.png
for_django_projects/pwa/static/images/icons/icon-144x144.png
for_django_projects/pwa/static/images/icons/icon-152x152.png
for_django_projects/pwa/static/images/icons/icon-192x192.png
for_django_projects/pwa/static/images/icons/icon-384x384.png
for_django_projects/pwa/static/images/icons/icon-512x512.png
for_django_projects/pwa/static/images/icons/icon-72x72.png
for_django_projects/pwa/static/images/icons/icon-96x96.png
for_django_projects/pwa/static/images/icons/splash-1125x2436.png
for_django_projects-1.3.3.dist-info/METADATA
for_django_projects-1.3.3.dist-info/WHEEL
for_django_projects-1.3.3.dist-info/top_level.txt
for_django_projects-1.3.3.dist-info/RECORD
