Metadata-Version: 2.1
Name: for-django-projects
Version: 1.3.3
Summary: Package of libraries for Django projects
Home-page: https://github.com/jasmanysanchez/for-django-projects
Author: Jasmany Sanchez Mendez
Author-email: jasmanysanchez97@gmail.com
License: UNKNOWN
Platform: UNKNOWN
Classifier: Programming Language :: Python :: 3
Classifier: License :: OSI Approved :: MIT License
Classifier: Operating System :: OS Independent
Requires-Python: >=3.6
Requires-Dist: Django (>=2.2)
